jquantum/__init__.py
jquantum/client.py
jquantum/compress.py
jquantum/converter.py
jquantum/params_compressor.py
jquantum/params_generator.py
jquantum/pattern_code.py
jquantum-0.1.4.dist-info/licenses/LICENSE
jquantum-0.1.4.dist-info/METADATA
jquantum-0.1.4.dist-info/WHEEL
jquantum-0.1.4.dist-info/top_level.txt
jquantum-0.1.4.dist-info/RECORD
