Metadata-Version: 2.4
Name: jquantum
Version: 0.1.4
Summary: Quantum circuit parameter compression and generation toolkit
Author-email: Jian Qi <e.jianqi@gmail.com>
License: MIT
Project-URL: Homepage, https://github.com/Jian-GitHub/Jian-Unified-System-Go/tree/main/jquantum/jquantum-py
Project-URL: Repository, https://github.com/Jian-GitHub/Jian-Unified-System-Go/tree/main/jquantum/jquantum-py
Keywords: quantum,qiskit,quest,compression,circuit,simulation
Classifier: Programming Language :: Python :: 3
Classifier: License :: OSI Approved :: MIT License
Classifier: Operating System :: OS Independent
Classifier: Topic :: Scientific/Engineering :: Physics
Classifier: Intended Audience :: Science/Research
Requires-Python: >=3.10
License-File: LICENSE
Requires-Dist: qiskit
Requires-Dist: numpy
Dynamic: license-file
